{"mcBlock":{"windows":10000,"pct5x":0,"pctRuin":1.6,"p90":1.281,"pctGain":35.1,"p10":0.64,"median":0.896,"pct17x":0,"mean":0.937,"label":"mc-block","pct10x":0,"worst":0.443,"best":2.594,"pct2x":0.18},"trades":699,"dailyRows":1095,"maxLosingStreakTrades":12,"ruinLevel":0.5,"historical":{"windows":1065,"pct5x":0,"pctRuin":2.8,"p90":1.307,"pctGain":34.6,"p10":0.616,"median":0.902,"pct17x":0,"mean":0.939,"label":"historical","pct10x":0,"worst":0.459,"best":1.819,"avgTradesPerWindow":19.1,"pct2x":0},"invariants":{"multiEntryDays":0,"ok":true,"stopOutsideLiq":0,"liqWithoutGap":0},"tag":"is_s3_tp","mcIid":{"windows":10000,"pct5x":0,"pctRuin":2.4,"p90":1.324,"pctGain":37,"p10":0.626,"median":0.903,"pct17x":0,"mean":0.949,"label":"mc-iid","pct10x":0,"worst":0.436,"best":2.884,"pct2x":0.42},"maxLosingStreakDays":10,"windowDays":30}