[
    {
        "day":  "2024-01-03",
        "ts":  1704240000000,
        "equity":  10000
    },
    {
        "day":  "2024-01-04",
        "ts":  1704326400000,
        "equity":  9862.77
    },
    {
        "day":  "2024-01-05",
        "ts":  1704412800000,
        "equity":  9745.73
    },
    {
        "day":  "2024-01-08",
        "ts":  1704672000000,
        "equity":  9570.18
    },
    {
        "day":  "2024-01-09",
        "ts":  1704758400000,
        "equity":  9722.94
    },
    {
        "day":  "2024-01-10",
        "ts":  1704844800000,
        "equity":  9711.1
    },
    {
        "day":  "2024-01-11",
        "ts":  1704931200000,
        "equity":  9874.71
    },
    {
        "day":  "2024-01-12",
        "ts":  1705017600000,
        "equity":  9880.21
    },
    {
        "day":  "2024-01-15",
        "ts":  1705276800000,
        "equity":  9956.13
    },
    {
        "day":  "2024-01-16",
        "ts":  1705363200000,
        "equity":  9901.97
    },
    {
        "day":  "2024-01-17",
        "ts":  1705449600000,
        "equity":  9505.88
    },
    {
        "day":  "2024-01-18",
        "ts":  1705536000000,
        "equity":  9491.93
    },
    {
        "day":  "2024-01-19",
        "ts":  1705622400000,
        "equity":  9692.94
    },
    {
        "day":  "2024-01-22",
        "ts":  1705881600000,
        "equity":  9815.53
    },
    {
        "day":  "2024-01-23",
        "ts":  1705968000000,
        "equity":  9735.44
    },
    {
        "day":  "2024-01-24",
        "ts":  1706054400000,
        "equity":  9595.86
    },
    {
        "day":  "2024-01-25",
        "ts":  1706140800000,
        "equity":  9549.52
    },
    {
        "day":  "2024-01-26",
        "ts":  1706227200000,
        "equity":  9483.7
    },
    {
        "day":  "2024-01-29",
        "ts":  1706486400000,
        "equity":  9658.62
    },
    {
        "day":  "2024-01-30",
        "ts":  1706572800000,
        "equity":  9551.27
    },
    {
        "day":  "2024-01-31",
        "ts":  1706659200000,
        "equity":  9525.92
    },
    {
        "day":  "2024-02-01",
        "ts":  1706745600000,
        "equity":  9342.33
    },
    {
        "day":  "2024-02-02",
        "ts":  1706832000000,
        "equity":  9274.08
    },
    {
        "day":  "2024-02-05",
        "ts":  1707091200000,
        "equity":  9397.96
    },
    {
        "day":  "2024-02-06",
        "ts":  1707177600000,
        "equity":  9291.85
    },
    {
        "day":  "2024-02-07",
        "ts":  1707264000000,
        "equity":  9391.14
    },
    {
        "day":  "2024-02-08",
        "ts":  1707350400000,
        "equity":  9591.72
    },
    {
        "day":  "2024-02-09",
        "ts":  1707436800000,
        "equity":  9487.32
    },
    {
        "day":  "2024-02-12",
        "ts":  1707696000000,
        "equity":  9512.97
    },
    {
        "day":  "2024-02-13",
        "ts":  1707782400000,
        "equity":  9551.46
    },
    {
        "day":  "2024-02-14",
        "ts":  1707868800000,
        "equity":  9525
    },
    {
        "day":  "2024-02-15",
        "ts":  1707955200000,
        "equity":  9369.92
    },
    {
        "day":  "2024-02-16",
        "ts":  1708041600000,
        "equity":  9274.1
    },
    {
        "day":  "2024-02-19",
        "ts":  1708300800000,
        "equity":  9217.52
    },
    {
        "day":  "2024-02-20",
        "ts":  1708387200000,
        "equity":  9208.59
    },
    {
        "day":  "2024-02-21",
        "ts":  1708473600000,
        "equity":  9166.91
    },
    {
        "day":  "2024-02-22",
        "ts":  1708560000000,
        "equity":  9176.88
    },
    {
        "day":  "2024-02-26",
        "ts":  1708905600000,
        "equity":  9288.65
    },
    {
        "day":  "2024-02-27",
        "ts":  1708992000000,
        "equity":  9300.5
    },
    {
        "day":  "2024-02-28",
        "ts":  1709078400000,
        "equity":  9327.23
    },
    {
        "day":  "2024-02-29",
        "ts":  1709164800000,
        "equity":  9244.97
    },
    {
        "day":  "2024-03-01",
        "ts":  1709251200000,
        "equity":  9101.2
    },
    {
        "day":  "2024-03-04",
        "ts":  1709510400000,
        "equity":  8860.33
    },
    {
        "day":  "2024-03-05",
        "ts":  1709596800000,
        "equity":  8907.62
    },
    {
        "day":  "2024-03-06",
        "ts":  1709683200000,
        "equity":  8924.33
    },
    {
        "day":  "2024-03-07",
        "ts":  1709769600000,
        "equity":  8887.39
    },
    {
        "day":  "2024-03-11",
        "ts":  1710115200000,
        "equity":  8886.51
    },
    {
        "day":  "2024-03-12",
        "ts":  1710201600000,
        "equity":  8754.58
    },
    {
        "day":  "2024-03-13",
        "ts":  1710288000000,
        "equity":  8771.98
    },
    {
        "day":  "2024-03-14",
        "ts":  1710374400000,
        "equity":  8803.5
    },
    {
        "day":  "2024-03-15",
        "ts":  1710460800000,
        "equity":  8855.78
    },
    {
        "day":  "2024-03-18",
        "ts":  1710720000000,
        "equity":  8798.43
    },
    {
        "day":  "2024-03-19",
        "ts":  1710806400000,
        "equity":  8755.11
    },
    {
        "day":  "2024-03-20",
        "ts":  1710892800000,
        "equity":  8857.13
    },
    {
        "day":  "2024-03-21",
        "ts":  1710979200000,
        "equity":  9083.59
    },
    {
        "day":  "2024-03-22",
        "ts":  1711065600000,
        "equity":  8841.25
    },
    {
        "day":  "2024-03-25",
        "ts":  1711324800000,
        "equity":  8583.75
    },
    {
        "day":  "2024-03-26",
        "ts":  1711411200000,
        "equity":  8585.8
    },
    {
        "day":  "2024-03-27",
        "ts":  1711497600000,
        "equity":  8571.45
    },
    {
        "day":  "2024-03-28",
        "ts":  1711584000000,
        "equity":  8579.37
    },
    {
        "day":  "2024-03-29",
        "ts":  1711670400000,
        "equity":  8607.76
    },
    {
        "day":  "2024-04-01",
        "ts":  1711929600000,
        "equity":  8692.34
    },
    {
        "day":  "2024-04-02",
        "ts":  1712016000000,
        "equity":  8674.23
    },
    {
        "day":  "2024-04-03",
        "ts":  1712102400000,
        "equity":  8740.57
    },
    {
        "day":  "2024-04-04",
        "ts":  1712188800000,
        "equity":  8749.36
    },
    {
        "day":  "2024-04-05",
        "ts":  1712275200000,
        "equity":  8702.82
    },
    {
        "day":  "2024-04-08",
        "ts":  1712534400000,
        "equity":  8756.52
    },
    {
        "day":  "2024-04-09",
        "ts":  1712620800000,
        "equity":  8698.53
    },
    {
        "day":  "2024-04-10",
        "ts":  1712707200000,
        "equity":  8767.58
    },
    {
        "day":  "2024-04-11",
        "ts":  1712793600000,
        "equity":  8775.95
    },
    {
        "day":  "2024-04-12",
        "ts":  1712880000000,
        "equity":  8841.26
    },
    {
        "day":  "2024-04-15",
        "ts":  1713139200000,
        "equity":  8853.3
    },
    {
        "day":  "2024-04-16",
        "ts":  1713225600000,
        "equity":  8806.31
    },
    {
        "day":  "2024-04-17",
        "ts":  1713312000000,
        "equity":  8736.37
    },
    {
        "day":  "2024-04-18",
        "ts":  1713398400000,
        "equity":  8679.65
    },
    {
        "day":  "2024-04-19",
        "ts":  1713484800000,
        "equity":  8667.2
    },
    {
        "day":  "2024-04-22",
        "ts":  1713744000000,
        "equity":  8655.96
    },
    {
        "day":  "2024-04-23",
        "ts":  1713830400000,
        "equity":  8503.87
    },
    {
        "day":  "2024-04-24",
        "ts":  1713916800000,
        "equity":  8449.51
    },
    {
        "day":  "2024-04-25",
        "ts":  1714003200000,
        "equity":  8454.57
    },
    {
        "day":  "2024-04-26",
        "ts":  1714089600000,
        "equity":  8378.66
    },
    {
        "day":  "2024-04-27",
        "ts":  1714176000000,
        "equity":  8322.81
    },
    {
        "day":  "2024-04-29",
        "ts":  1714348800000,
        "equity":  8305.62
    },
    {
        "day":  "2024-04-30",
        "ts":  1714435200000,
        "equity":  8292.02
    },
    {
        "day":  "2024-05-02",
        "ts":  1714608000000,
        "equity":  8279.13
    },
    {
        "day":  "2024-05-03",
        "ts":  1714694400000,
        "equity":  8322.81
    },
    {
        "day":  "2024-05-06",
        "ts":  1714953600000,
        "equity":  8309.92
    },
    {
        "day":  "2024-05-07",
        "ts":  1715040000000,
        "equity":  8352.21
    },
    {
        "day":  "2024-05-08",
        "ts":  1715126400000,
        "equity":  8416.43
    },
    {
        "day":  "2024-05-10",
        "ts":  1715299200000,
        "equity":  8684.23
    },
    {
        "day":  "2024-05-13",
        "ts":  1715558400000,
        "equity":  8718.8
    },
    {
        "day":  "2024-05-14",
        "ts":  1715644800000,
        "equity":  8793.41
    },
    {
        "day":  "2024-05-15",
        "ts":  1715731200000,
        "equity":  9049.45
    },
    {
        "day":  "2024-05-16",
        "ts":  1715817600000,
        "equity":  9123.23
    },
    {
        "day":  "2024-05-17",
        "ts":  1715904000000,
        "equity":  9339.62
    },
    {
        "day":  "2024-05-20",
        "ts":  1716163200000,
        "equity":  9298.87
    },
    {
        "day":  "2024-05-21",
        "ts":  1716249600000,
        "equity":  9283.11
    },
    {
        "day":  "2024-05-22",
        "ts":  1716336000000,
        "equity":  9255.27
    },
    {
        "day":  "2024-05-23",
        "ts":  1716422400000,
        "equity":  9176.47
    },
    {
        "day":  "2024-05-24",
        "ts":  1716508800000,
        "equity":  9135.57
    },
    {
        "day":  "2024-05-27",
        "ts":  1716768000000,
        "equity":  9210.4
    },
    {
        "day":  "2024-05-28",
        "ts":  1716854400000,
        "equity":  9246.56
    },
    {
        "day":  "2024-05-29",
        "ts":  1716940800000,
        "equity":  9253.59
    },
    {
        "day":  "2024-05-30",
        "ts":  1717027200000,
        "equity":  9180.28
    },
    {
        "day":  "2024-05-31",
        "ts":  1717113600000,
        "equity":  9084.87
    },
    {
        "day":  "2024-06-03",
        "ts":  1717372800000,
        "equity":  9091.9
    },
    {
        "day":  "2024-06-04",
        "ts":  1717459200000,
        "equity":  9000.31
    },
    {
        "day":  "2024-06-05",
        "ts":  1717545600000,
        "equity":  9026.78
    },
    {
        "day":  "2024-06-06",
        "ts":  1717632000000,
        "equity":  9273.39
    },
    {
        "day":  "2024-06-07",
        "ts":  1717718400000,
        "equity":  8728.58
    },
    {
        "day":  "2024-06-10",
        "ts":  1717977600000,
        "equity":  8911.53
    },
    {
        "day":  "2024-06-11",
        "ts":  1718064000000,
        "equity":  8881.99
    },
    {
        "day":  "2024-06-13",
        "ts":  1718236800000,
        "equity":  8815.53
    },
    {
        "day":  "2024-06-14",
        "ts":  1718323200000,
        "equity":  8801.5
    },
    {
        "day":  "2024-06-17",
        "ts":  1718582400000,
        "equity":  8706.15
    },
    {
        "day":  "2024-06-18",
        "ts":  1718668800000,
        "equity":  8706.15
    },
    {
        "day":  "2024-06-19",
        "ts":  1718755200000,
        "equity":  8706.15
    },
    {
        "day":  "2024-06-20",
        "ts":  1718841600000,
        "equity":  8706.15
    },
    {
        "day":  "2024-06-21",
        "ts":  1718928000000,
        "equity":  8454.65
    },
    {
        "day":  "2024-06-24",
        "ts":  1719187200000,
        "equity":  8378.28
    },
    {
        "day":  "2024-06-25",
        "ts":  1719273600000,
        "equity":  8284.93
    },
    {
        "day":  "2024-06-26",
        "ts":  1719360000000,
        "equity":  8172.33
    },
    {
        "day":  "2024-06-27",
        "ts":  1719446400000,
        "equity":  8172.33
    },
    {
        "day":  "2024-06-28",
        "ts":  1719532800000,
        "equity":  8172.33
    },
    {
        "day":  "2024-07-01",
        "ts":  1719792000000,
        "equity":  8172.33
    },
    {
        "day":  "2024-07-02",
        "ts":  1719878400000,
        "equity":  8131.24
    },
    {
        "day":  "2024-07-03",
        "ts":  1719964800000,
        "equity":  8342.15
    },
    {
        "day":  "2024-07-04",
        "ts":  1720051200000,
        "equity":  8307.33
    },
    {
        "day":  "2024-07-05",
        "ts":  1720137600000,
        "equity":  8154.7
    },
    {
        "day":  "2024-07-08",
        "ts":  1720396800000,
        "equity":  8078.83
    },
    {
        "day":  "2024-07-09",
        "ts":  1720483200000,
        "equity":  8230.79
    },
    {
        "day":  "2024-07-10",
        "ts":  1720569600000,
        "equity":  8373.68
    },
    {
        "day":  "2024-07-11",
        "ts":  1720656000000,
        "equity":  8516.52
    },
    {
        "day":  "2024-07-12",
        "ts":  1720742400000,
        "equity":  8503.88
    },
    {
        "day":  "2024-07-15",
        "ts":  1721001600000,
        "equity":  8626.38
    },
    {
        "day":  "2024-07-16",
        "ts":  1721088000000,
        "equity":  8650.03
    },
    {
        "day":  "2024-07-17",
        "ts":  1721174400000,
        "equity":  8777.61
    },
    {
        "day":  "2024-07-18",
        "ts":  1721260800000,
        "equity":  8630.91
    },
    {
        "day":  "2024-07-19",
        "ts":  1721347200000,
        "equity":  8551.73
    },
    {
        "day":  "2024-07-22",
        "ts":  1721606400000,
        "equity":  8397.11
    },
    {
        "day":  "2024-07-23",
        "ts":  1721692800000,
        "equity":  8502.62
    },
    {
        "day":  "2024-07-24",
        "ts":  1721779200000,
        "equity":  8681.28
    },
    {
        "day":  "2024-07-25",
        "ts":  1721865600000,
        "equity":  8348.41
    },
    {
        "day":  "2024-07-26",
        "ts":  1721952000000,
        "equity":  8262.78
    },
    {
        "day":  "2024-07-29",
        "ts":  1722211200000,
        "equity":  8620.49
    },
    {
        "day":  "2024-07-30",
        "ts":  1722297600000,
        "equity":  8398.24
    },
    {
        "day":  "2024-07-31",
        "ts":  1722384000000,
        "equity":  8461.21
    },
    {
        "day":  "2024-08-01",
        "ts":  1722470400000,
        "equity":  8560.44
    },
    {
        "day":  "2024-08-02",
        "ts":  1722556800000,
        "equity":  8789.73
    },
    {
        "day":  "2024-08-05",
        "ts":  1722816000000,
        "equity":  9139.34
    },
    {
        "day":  "2024-08-06",
        "ts":  1722902400000,
        "equity":  9106.28
    },
    {
        "day":  "2024-08-07",
        "ts":  1722988800000,
        "equity":  8951.82
    },
    {
        "day":  "2024-08-08",
        "ts":  1723075200000,
        "equity":  9079.63
    },
    {
        "day":  "2024-08-09",
        "ts":  1723161600000,
        "equity":  9088.89
    },
    {
        "day":  "2024-08-12",
        "ts":  1723420800000,
        "equity":  9119.58
    },
    {
        "day":  "2024-08-13",
        "ts":  1723507200000,
        "equity":  9072.78
    },
    {
        "day":  "2024-08-14",
        "ts":  1723593600000,
        "equity":  9056.02
    },
    {
        "day":  "2024-08-15",
        "ts":  1723680000000,
        "equity":  9042.29
    },
    {
        "day":  "2024-08-16",
        "ts":  1723766400000,
        "equity":  9237.36
    },
    {
        "day":  "2024-08-19",
        "ts":  1724025600000,
        "equity":  9511.89
    },
    {
        "day":  "2024-08-20",
        "ts":  1724112000000,
        "equity":  9763.13
    },
    {
        "day":  "2024-08-21",
        "ts":  1724198400000,
        "equity":  9757.16
    },
    {
        "day":  "2024-08-22",
        "ts":  1724284800000,
        "equity":  9865.92
    },
    {
        "day":  "2024-08-23",
        "ts":  1724371200000,
        "equity":  9928.61
    },
    {
        "day":  "2024-08-26",
        "ts":  1724630400000,
        "equity":  9585.69
    },
    {
        "day":  "2024-08-27",
        "ts":  1724716800000,
        "equity":  9696.8
    },
    {
        "day":  "2024-08-28",
        "ts":  1724803200000,
        "equity":  9763.82
    },
    {
        "day":  "2024-08-29",
        "ts":  1724889600000,
        "equity":  9666.56
    },
    {
        "day":  "2024-08-30",
        "ts":  1724976000000,
        "equity":  10036.92
    },
    {
        "day":  "2024-09-02",
        "ts":  1725235200000,
        "equity":  10245.76
    },
    {
        "day":  "2024-09-03",
        "ts":  1725321600000,
        "equity":  10598.21
    },
    {
        "day":  "2024-09-04",
        "ts":  1725408000000,
        "equity":  10448.07
    },
    {
        "day":  "2024-09-05",
        "ts":  1725494400000,
        "equity":  10414.38
    },
    {
        "day":  "2024-09-06",
        "ts":  1725580800000,
        "equity":  10548.32
    },
    {
        "day":  "2024-09-09",
        "ts":  1725840000000,
        "equity":  10382.81
    },
    {
        "day":  "2024-09-10",
        "ts":  1725926400000,
        "equity":  10596.11
    },
    {
        "day":  "2024-09-11",
        "ts":  1726012800000,
        "equity":  10557.35
    },
    {
        "day":  "2024-09-12",
        "ts":  1726099200000,
        "equity":  10584.04
    },
    {
        "day":  "2024-09-13",
        "ts":  1726185600000,
        "equity":  10408.82
    },
    {
        "day":  "2024-09-16",
        "ts":  1726444800000,
        "equity":  10272.5
    },
    {
        "day":  "2024-09-17",
        "ts":  1726531200000,
        "equity":  10193.71
    },
    {
        "day":  "2024-09-18",
        "ts":  1726617600000,
        "equity":  10230.36
    },
    {
        "day":  "2024-09-19",
        "ts":  1726704000000,
        "equity":  10123.06
    },
    {
        "day":  "2024-09-20",
        "ts":  1726790400000,
        "equity":  10123.06
    },
    {
        "day":  "2024-09-23",
        "ts":  1727049600000,
        "equity":  10123.06
    },
    {
        "day":  "2024-09-24",
        "ts":  1727136000000,
        "equity":  10123.06
    },
    {
        "day":  "2024-09-25",
        "ts":  1727222400000,
        "equity":  10123.06
    },
    {
        "day":  "2024-09-26",
        "ts":  1727308800000,
        "equity":  10123.06
    },
    {
        "day":  "2024-09-27",
        "ts":  1727395200000,
        "equity":  10123.06
    },
    {
        "day":  "2024-09-30",
        "ts":  1727654400000,
        "equity":  10123.06
    },
    {
        "day":  "2024-10-01",
        "ts":  1727740800000,
        "equity":  10123.06
    },
    {
        "day":  "2024-10-02",
        "ts":  1727827200000,
        "equity":  10359.18
    },
    {
        "day":  "2024-10-03",
        "ts":  1727913600000,
        "equity":  10271.5
    },
    {
        "day":  "2024-10-04",
        "ts":  1728000000000,
        "equity":  10192.92
    },
    {
        "day":  "2024-10-07",
        "ts":  1728259200000,
        "equity":  10263.71
    },
    {
        "day":  "2024-10-08",
        "ts":  1728345600000,
        "equity":  10268.05
    },
    {
        "day":  "2024-10-09",
        "ts":  1728432000000,
        "equity":  10500.71
    },
    {
        "day":  "2024-10-10",
        "ts":  1728518400000,
        "equity":  10401.45
    },
    {
        "day":  "2024-10-11",
        "ts":  1728604800000,
        "equity":  10339.85
    },
    {
        "day":  "2024-10-14",
        "ts":  1728864000000,
        "equity":  10197.5
    },
    {
        "day":  "2024-10-15",
        "ts":  1728950400000,
        "equity":  10277.3
    },
    {
        "day":  "2024-10-16",
        "ts":  1729036800000,
        "equity":  10409.96
    },
    {
        "day":  "2024-10-17",
        "ts":  1729123200000,
        "equity":  10405.88
    },
    {
        "day":  "2024-10-18",
        "ts":  1729209600000,
        "equity":  10621.97
    },
    {
        "day":  "2024-10-21",
        "ts":  1729468800000,
        "equity":  10885.74
    },
    {
        "day":  "2024-10-22",
        "ts":  1729555200000,
        "equity":  11112.93
    },
    {
        "day":  "2024-10-23",
        "ts":  1729641600000,
        "equity":  11151.26
    },
    {
        "day":  "2024-10-24",
        "ts":  1729728000000,
        "equity":  11175.71
    },
    {
        "day":  "2024-10-25",
        "ts":  1729814400000,
        "equity":  11466.25
    },
    {
        "day":  "2024-10-28",
        "ts":  1730073600000,
        "equity":  11851.66
    },
    {
        "day":  "2024-10-29",
        "ts":  1730160000000,
        "equity":  11846.86
    },
    {
        "day":  "2024-10-30",
        "ts":  1730246400000,
        "equity":  11773.23
    },
    {
        "day":  "2024-10-31",
        "ts":  1730332800000,
        "equity":  11762.64
    },
    {
        "day":  "2024-11-01",
        "ts":  1730419200000,
        "equity":  11718.37
    },
    {
        "day":  "2024-11-02",
        "ts":  1730505600000,
        "equity":  11702.11
    },
    {
        "day":  "2024-11-05",
        "ts":  1730764800000,
        "equity":  11650.35
    },
    {
        "day":  "2024-11-06",
        "ts":  1730851200000,
        "equity":  11568.37
    },
    {
        "day":  "2024-11-07",
        "ts":  1730937600000,
        "equity":  11481.53
    },
    {
        "day":  "2024-11-08",
        "ts":  1731024000000,
        "equity":  11386.16
    },
    {
        "day":  "2024-11-11",
        "ts":  1731283200000,
        "equity":  11578.74
    },
    {
        "day":  "2024-11-12",
        "ts":  1731369600000,
        "equity":  11533.71
    },
    {
        "day":  "2024-11-13",
        "ts":  1731456000000,
        "equity":  11556.04
    },
    {
        "day":  "2024-11-14",
        "ts":  1731542400000,
        "equity":  11911.66
    },
    {
        "day":  "2024-11-15",
        "ts":  1731628800000,
        "equity":  11762.42
    },
    {
        "day":  "2024-11-18",
        "ts":  1731888000000,
        "equity":  11836.13
    },
    {
        "day":  "2024-11-19",
        "ts":  1731974400000,
        "equity":  12353.63
    },
    {
        "day":  "2024-11-20",
        "ts":  1732060800000,
        "equity":  12576.6
    },
    {
        "day":  "2024-11-21",
        "ts":  1732147200000,
        "equity":  12660.98
    },
    {
        "day":  "2024-11-22",
        "ts":  1732233600000,
        "equity":  12626.57
    },
    {
        "day":  "2024-11-25",
        "ts":  1732492800000,
        "equity":  13262.29
    },
    {
        "day":  "2024-11-26",
        "ts":  1732579200000,
        "equity":  13576.72
    },
    {
        "day":  "2024-11-27",
        "ts":  1732665600000,
        "equity":  13627.25
    },
    {
        "day":  "2024-11-28",
        "ts":  1732752000000,
        "equity":  13408.24
    },
    {
        "day":  "2024-11-29",
        "ts":  1732838400000,
        "equity":  13152.29
    },
    {
        "day":  "2024-12-02",
        "ts":  1733097600000,
        "equity":  13231.65
    },
    {
        "day":  "2024-12-03",
        "ts":  1733184000000,
        "equity":  13221.03
    },
    {
        "day":  "2024-12-04",
        "ts":  1733270400000,
        "equity":  13413.46
    },
    {
        "day":  "2024-12-05",
        "ts":  1733356800000,
        "equity":  13213.69
    },
    {
        "day":  "2024-12-06",
        "ts":  1733443200000,
        "equity":  13207.29
    },
    {
        "day":  "2024-12-09",
        "ts":  1733702400000,
        "equity":  12958.97
    },
    {
        "day":  "2024-12-10",
        "ts":  1733788800000,
        "equity":  13038.39
    },
    {
        "day":  "2024-12-11",
        "ts":  1733875200000,
        "equity":  12662.68
    },
    {
        "day":  "2024-12-12",
        "ts":  1733961600000,
        "equity":  12731.51
    },
    {
        "day":  "2024-12-13",
        "ts":  1734048000000,
        "equity":  12434.05
    },
    {
        "day":  "2024-12-16",
        "ts":  1734307200000,
        "equity":  12448.55
    },
    {
        "day":  "2024-12-17",
        "ts":  1734393600000,
        "equity":  12555.24
    },
    {
        "day":  "2024-12-18",
        "ts":  1734480000000,
        "equity":  12593.38
    },
    {
        "day":  "2024-12-19",
        "ts":  1734566400000,
        "equity":  12851.58
    },
    {
        "day":  "2024-12-20",
        "ts":  1734652800000,
        "equity":  12714.58
    },
    {
        "day":  "2024-12-23",
        "ts":  1734912000000,
        "equity":  12852.36
    },
    {
        "day":  "2024-12-24",
        "ts":  1734998400000,
        "equity":  12813.08
    },
    {
        "day":  "2024-12-25",
        "ts":  1735084800000,
        "equity":  12868.53
    },
    {
        "day":  "2024-12-26",
        "ts":  1735171200000,
        "equity":  12393.69
    },
    {
        "day":  "2024-12-27",
        "ts":  1735257600000,
        "equity":  12420.9
    },
    {
        "day":  "2024-12-28",
        "ts":  1735344000000,
        "equity":  12453.78
    },
    {
        "day":  "2024-12-30",
        "ts":  1735516800000,
        "equity":  12831.31
    }
]
