{
    "scannedUtc":  "2026-07-19 20:20",
    "strategy":  "v2",
    "btcTrend":  "up",
    "flatBlockAll":  false,
    "fng":  28,
    "closedBarUtc":  "2026-07-19 16:00",
    "signals":  [

                ],
    "watch":  [
                  {
                      "symbol":  "BTC-USDT",
                      "side":  null,
                      "trend":  "up",
                      "dir":  "long",
                      "price":  64433.4,
                      "ema20":  64263.203175,
                      "ema50":  63951.546532,
                      "ema200":  64139.759677,
                      "rsi":  53.8,
                      "atrPct":  0.77,
                      "funding8h":  8.7E-05,
                      "barTime":  1784476800000,
                      "distZonePct":  0.26,
                      "sub":  {
                                  "trendOk":  true,
                                  "pullback":  false,
                                  "rsiReset":  false,
                                  "triggerBar":  false
                              },
                      "checks":  {
                                     "setupA":  false,
                                     "btcFilter":  true,
                                     "flatMode":  true,
                                     "atrCap":  true,
                                     "funding":  true,
                                     "fearGreed":  true
                                 },
                      "pass":  false,
                      "entry":  null,
                      "stop":  null,
                      "tp1":  null,
                      "stopPct":  null,
                      "rr":  null,
                      "qty":  null,
                      "riskUsd":  100.17
                  },
                  {
                      "symbol":  "ETH-USDT",
                      "side":  null,
                      "trend":  "up",
                      "dir":  "long",
                      "price":  1861.5,
                      "ema20":  1858.445214,
                      "ema50":  1839.457453,
                      "ema200":  1792.639569,
                      "rsi":  53,
                      "atrPct":  1.08,
                      "funding8h":  3.2E-05,
                      "barTime":  1784476800000,
                      "distZonePct":  0.16,
                      "sub":  {
                                  "trendOk":  true,
                                  "pullback":  false,
                                  "rsiReset":  false,
                                  "triggerBar":  false
                              },
                      "checks":  {
                                     "setupA":  false,
                                     "btcFilter":  true,
                                     "flatMode":  true,
                                     "atrCap":  true,
                                     "funding":  true,
                                     "fearGreed":  true
                                 },
                      "pass":  false,
                      "entry":  null,
                      "stop":  null,
                      "tp1":  null,
                      "stopPct":  null,
                      "rr":  null,
                      "qty":  null,
                      "riskUsd":  100.17
                  },
                  {
                      "symbol":  "SOL-USDT",
                      "side":  null,
                      "trend":  "down",
                      "dir":  "down",
                      "price":  75.839,
                      "ema20":  75.724881,
                      "ema50":  76.277571,
                      "ema200":  76.482144,
                      "rsi":  50,
                      "atrPct":  1.13,
                      "funding8h":  5.6E-05,
                      "barTime":  1784476800000,
                      "distZonePct":  0,
                      "sub":  {
                                  "trendOk":  true,
                                  "pullback":  true,
                                  "rsiReset":  true,
                                  "triggerBar":  false
                              },
                      "checks":  {
                                     "setupA":  false,
                                     "btcFilter":  true,
                                     "flatMode":  true,
                                     "atrCap":  true,
                                     "funding":  true,
                                     "fearGreed":  true
                                 },
                      "pass":  false,
                      "entry":  null,
                      "stop":  null,
                      "tp1":  null,
                      "stopPct":  null,
                      "rr":  null,
                      "qty":  null,
                      "riskUsd":  100.17
                  },
                  {
                      "symbol":  "BNB-USDT",
                      "side":  null,
                      "trend":  "down",
                      "dir":  "down",
                      "price":  567.94,
                      "ema20":  570.204685,
                      "ema50":  572.011055,
                      "ema200":  580.964964,
                      "rsi":  43.2,
                      "atrPct":  0.72,
                      "funding8h":  1E-06,
                      "barTime":  1784476800000,
                      "distZonePct":  -0.4,
                      "sub":  {
                                  "trendOk":  true,
                                  "pullback":  true,
                                  "rsiReset":  false,
                                  "triggerBar":  false
                              },
                      "checks":  {
                                     "setupA":  false,
                                     "btcFilter":  true,
                                     "flatMode":  true,
                                     "atrCap":  true,
                                     "funding":  true,
                                     "fearGreed":  true
                                 },
                      "pass":  false,
                      "entry":  null,
                      "stop":  null,
                      "tp1":  null,
                      "stopPct":  null,
                      "rr":  null,
                      "qty":  null,
                      "riskUsd":  100.17
                  },
                  {
                      "symbol":  "XRP-USDT",
                      "side":  null,
                      "trend":  "down",
                      "dir":  "down",
                      "price":  1.094,
                      "ema20":  1.093518,
                      "ema50":  1.095399,
                      "ema200":  1.122943,
                      "rsi":  50.1,
                      "atrPct":  0.94,
                      "funding8h":  9.3E-05,
                      "barTime":  1784476800000,
                      "distZonePct":  0,
                      "sub":  {
                                  "trendOk":  true,
                                  "pullback":  true,
                                  "rsiReset":  true,
                                  "triggerBar":  false
                              },
                      "checks":  {
                                     "setupA":  false,
                                     "btcFilter":  true,
                                     "flatMode":  true,
                                     "atrCap":  true,
                                     "funding":  true,
                                     "fearGreed":  true
                                 },
                      "pass":  false,
                      "entry":  null,
                      "stop":  null,
                      "tp1":  null,
                      "stopPct":  null,
                      "rr":  null,
                      "qty":  null,
                      "riskUsd":  100.17
                  },
                  {
                      "symbol":  "DOGE-USDT",
                      "side":  null,
                      "trend":  "down",
                      "dir":  "down",
                      "price":  0.07224,
                      "ema20":  0.072546,
                      "ema50":  0.072989,
                      "ema200":  0.077595,
                      "rsi":  43.5,
                      "atrPct":  1.03,
                      "funding8h":  0.0001,
                      "barTime":  1784476800000,
                      "distZonePct":  -0.42,
                      "sub":  {
                                  "trendOk":  true,
                                  "pullback":  true,
                                  "rsiReset":  false,
                                  "triggerBar":  false
                              },
                      "checks":  {
                                     "setupA":  false,
                                     "btcFilter":  true,
                                     "flatMode":  true,
                                     "atrCap":  true,
                                     "funding":  true,
                                     "fearGreed":  true
                                 },
                      "pass":  false,
                      "entry":  null,
                      "stop":  null,
                      "tp1":  null,
                      "stopPct":  null,
                      "rr":  null,
                      "qty":  null,
                      "riskUsd":  100.17
                  },
                  {
                      "symbol":  "ADA-USDT",
                      "side":  null,
                      "trend":  "up",
                      "dir":  "long",
                      "price":  0.1659,
                      "ema20":  0.164949,
                      "ema50":  0.16484,
                      "ema200":  0.170971,
                      "rsi":  54.1,
                      "atrPct":  1.74,
                      "funding8h":  0.0001,
                      "barTime":  1784476800000,
                      "distZonePct":  0.57,
                      "sub":  {
                                  "trendOk":  true,
                                  "pullback":  true,
                                  "rsiReset":  false,
                                  "triggerBar":  false
                              },
                      "checks":  {
                                     "setupA":  false,
                                     "btcFilter":  true,
                                     "flatMode":  true,
                                     "atrCap":  true,
                                     "funding":  true,
                                     "fearGreed":  true
                                 },
                      "pass":  false,
                      "entry":  null,
                      "stop":  null,
                      "tp1":  null,
                      "stopPct":  null,
                      "rr":  null,
                      "qty":  null,
                      "riskUsd":  100.17
                  },
                  {
                      "symbol":  "AVAX-USDT",
                      "side":  null,
                      "trend":  "down",
                      "dir":  "down",
                      "price":  6.431,
                      "ema20":  6.539922,
                      "ema50":  6.575074,
                      "ema200":  6.813498,
                      "rsi":  37.7,
                      "atrPct":  1.43,
                      "funding8h":  3E-05,
                      "barTime":  1784476800000,
                      "distZonePct":  -1.69,
                      "sub":  {
                                  "trendOk":  true,
                                  "pullback":  true,
                                  "rsiReset":  false,
                                  "triggerBar":  false
                              },
                      "checks":  {
                                     "setupA":  false,
                                     "btcFilter":  true,
                                     "flatMode":  true,
                                     "atrCap":  true,
                                     "funding":  true,
                                     "fearGreed":  true
                                 },
                      "pass":  false,
                      "entry":  null,
                      "stop":  null,
                      "tp1":  null,
                      "stopPct":  null,
                      "rr":  null,
                      "qty":  null,
                      "riskUsd":  100.17
                  },
                  {
                      "symbol":  "LINK-USDT",
                      "side":  null,
                      "trend":  "up",
                      "dir":  "long",
                      "price":  8.333,
                      "ema20":  8.309228,
                      "ema50":  8.21071,
                      "ema200":  8.075048,
                      "rsi":  54.9,
                      "atrPct":  1.15,
                      "funding8h":  0.0001,
                      "barTime":  1784476800000,
                      "distZonePct":  0.29,
                      "sub":  {
                                  "trendOk":  true,
                                  "pullback":  false,
                                  "rsiReset":  false,
                                  "triggerBar":  false
                              },
                      "checks":  {
                                     "setupA":  false,
                                     "btcFilter":  true,
                                     "flatMode":  true,
                                     "atrCap":  true,
                                     "funding":  true,
                                     "fearGreed":  true
                                 },
                      "pass":  false,
                      "entry":  null,
                      "stop":  null,
                      "tp1":  null,
                      "stopPct":  null,
                      "rr":  null,
                      "qty":  null,
                      "riskUsd":  100.17
                  },
                  {
                      "symbol":  "DOT-USDT",
                      "side":  null,
                      "trend":  "down",
                      "dir":  "down",
                      "price":  0.815,
                      "ema20":  0.837169,
                      "ema50":  0.843669,
                      "ema200":  0.896054,
                      "rsi":  31.5,
                      "atrPct":  1.7,
                      "funding8h":  -0.000183,
                      "barTime":  1784476800000,
                      "distZonePct":  -2.72,
                      "sub":  {
                                  "trendOk":  true,
                                  "pullback":  false,
                                  "rsiReset":  false,
                                  "triggerBar":  false
                              },
                      "checks":  {
                                     "setupA":  false,
                                     "btcFilter":  true,
                                     "flatMode":  true,
                                     "atrCap":  true,
                                     "funding":  true,
                                     "fearGreed":  true
                                 },
                      "pass":  false,
                      "entry":  null,
                      "stop":  null,
                      "tp1":  null,
                      "stopPct":  null,
                      "rr":  null,
                      "qty":  null,
                      "riskUsd":  100.17
                  },
                  {
                      "symbol":  "LTC-USDT",
                      "side":  null,
                      "trend":  "up",
                      "dir":  "long",
                      "price":  47.63,
                      "ema20":  46.136123,
                      "ema50":  45.334505,
                      "ema200":  45.060384,
                      "rsi":  72.1,
                      "atrPct":  1.4,
                      "funding8h":  0.0001,
                      "barTime":  1784476800000,
                      "distZonePct":  3.14,
                      "sub":  {
                                  "trendOk":  true,
                                  "pullback":  false,
                                  "rsiReset":  false,
                                  "triggerBar":  false
                              },
                      "checks":  {
                                     "setupA":  false,
                                     "btcFilter":  true,
                                     "flatMode":  true,
                                     "atrCap":  true,
                                     "funding":  true,
                                     "fearGreed":  true
                                 },
                      "pass":  false,
                      "entry":  null,
                      "stop":  null,
                      "tp1":  null,
                      "stopPct":  null,
                      "rr":  null,
                      "qty":  null,
                      "riskUsd":  100.17
                  },
                  {
                      "symbol":  "BCH-USDT",
                      "side":  null,
                      "trend":  "down",
                      "dir":  "down",
                      "price":  217.59,
                      "ema20":  220.442206,
                      "ema50":  226.069082,
                      "ema200":  234.081372,
                      "rsi":  36.5,
                      "atrPct":  1.48,
                      "funding8h":  0.0001,
                      "barTime":  1784476800000,
                      "distZonePct":  -1.31,
                      "sub":  {
                                  "trendOk":  true,
                                  "pullback":  false,
                                  "rsiReset":  false,
                                  "triggerBar":  false
                              },
                      "checks":  {
                                     "setupA":  false,
                                     "btcFilter":  true,
                                     "flatMode":  true,
                                     "atrCap":  true,
                                     "funding":  true,
                                     "fearGreed":  true
                                 },
                      "pass":  false,
                      "entry":  null,
                      "stop":  null,
                      "tp1":  null,
                      "stopPct":  null,
                      "rr":  null,
                      "qty":  null,
                      "riskUsd":  100.17
                  },
                  {
                      "symbol":  "UNI-USDT",
                      "side":  null,
                      "trend":  "range",
                      "dir":  null,
                      "price":  3.492,
                      "ema20":  3.545326,
                      "ema50":  3.533466,
                      "ema200":  3.29884,
                      "rsi":  42.8,
                      "atrPct":  2.03,
                      "funding8h":  -5.3E-05,
                      "barTime":  1784476800000,
                      "distZonePct":  -1.19,
                      "sub":  {
                                  "trendOk":  false,
                                  "pullback":  false,
                                  "rsiReset":  false,
                                  "triggerBar":  false
                              },
                      "checks":  {
                                     "setupA":  false,
                                     "btcFilter":  true,
                                     "flatMode":  true,
                                     "atrCap":  true,
                                     "funding":  true,
                                     "fearGreed":  true
                                 },
                      "pass":  false,
                      "entry":  null,
                      "stop":  null,
                      "tp1":  null,
                      "stopPct":  null,
                      "rr":  null,
                      "qty":  null,
                      "riskUsd":  100.17
                  },
                  {
                      "symbol":  "ATOM-USDT",
                      "side":  null,
                      "trend":  "down",
                      "dir":  "down",
                      "price":  1.478,
                      "ema20":  1.501547,
                      "ema50":  1.526036,
                      "ema200":  1.628903,
                      "rsi":  31,
                      "atrPct":  1.2,
                      "funding8h":  5.6E-05,
                      "barTime":  1784476800000,
                      "distZonePct":  -1.59,
                      "sub":  {
                                  "trendOk":  true,
                                  "pullback":  false,
                                  "rsiReset":  false,
                                  "triggerBar":  false
                              },
                      "checks":  {
                                     "setupA":  false,
                                     "btcFilter":  true,
                                     "flatMode":  true,
                                     "atrCap":  true,
                                     "funding":  true,
                                     "fearGreed":  true
                                 },
                      "pass":  false,
                      "entry":  null,
                      "stop":  null,
                      "tp1":  null,
                      "stopPct":  null,
                      "rr":  null,
                      "qty":  null,
                      "riskUsd":  100.17
                  },
                  {
                      "symbol":  "NEAR-USDT",
                      "side":  null,
                      "trend":  "down",
                      "dir":  "down",
                      "price":  1.917,
                      "ema20":  1.939617,
                      "ema50":  1.951052,
                      "ema200":  1.980416,
                      "rsi":  43.1,
                      "atrPct":  1.94,
                      "funding8h":  0.0001,
                      "barTime":  1784476800000,
                      "distZonePct":  -1.18,
                      "sub":  {
                                  "trendOk":  true,
                                  "pullback":  false,
                                  "rsiReset":  false,
                                  "triggerBar":  false
                              },
                      "checks":  {
                                     "setupA":  false,
                                     "btcFilter":  true,
                                     "flatMode":  true,
                                     "atrCap":  true,
                                     "funding":  true,
                                     "fearGreed":  true
                                 },
                      "pass":  false,
                      "entry":  null,
                      "stop":  null,
                      "tp1":  null,
                      "stopPct":  null,
                      "rr":  null,
                      "qty":  null,
                      "riskUsd":  100.17
                  },
                  {
                      "symbol":  "OP-USDT",
                      "side":  null,
                      "trend":  "down",
                      "dir":  "down",
                      "price":  0.0945,
                      "ema20":  0.096203,
                      "ema50":  0.098524,
                      "ema200":  0.103379,
                      "rsi":  35.7,
                      "atrPct":  1.85,
                      "funding8h":  0.0001,
                      "barTime":  1784476800000,
                      "distZonePct":  -1.8,
                      "sub":  {
                                  "trendOk":  true,
                                  "pullback":  false,
                                  "rsiReset":  false,
                                  "triggerBar":  false
                              },
                      "checks":  {
                                     "setupA":  false,
                                     "btcFilter":  true,
                                     "flatMode":  true,
                                     "atrCap":  true,
                                     "funding":  true,
                                     "fearGreed":  true
                                 },
                      "pass":  false,
                      "entry":  null,
                      "stop":  null,
                      "tp1":  null,
                      "stopPct":  null,
                      "rr":  null,
                      "qty":  null,
                      "riskUsd":  100.17
                  },
                  {
                      "symbol":  "APT-USDT",
                      "side":  null,
                      "trend":  "down",
                      "dir":  "down",
                      "price":  0.5934,
                      "ema20":  0.606735,
                      "ema50":  0.611506,
                      "ema200":  0.647101,
                      "rsi":  37.1,
                      "atrPct":  1.61,
                      "funding8h":  0.0001,
                      "barTime":  1784476800000,
                      "distZonePct":  -2.25,
                      "sub":  {
                                  "trendOk":  true,
                                  "pullback":  false,
                                  "rsiReset":  false,
                                  "triggerBar":  false
                              },
                      "checks":  {
                                     "setupA":  false,
                                     "btcFilter":  true,
                                     "flatMode":  true,
                                     "atrCap":  true,
                                     "funding":  true,
                                     "fearGreed":  true
                                 },
                      "pass":  false,
                      "entry":  null,
                      "stop":  null,
                      "tp1":  null,
                      "stopPct":  null,
                      "rr":  null,
                      "qty":  null,
                      "riskUsd":  100.17
                  },
                  {
                      "symbol":  "ARB-USDT",
                      "side":  null,
                      "trend":  "range",
                      "dir":  null,
                      "price":  0.08862,
                      "ema20":  0.089016,
                      "ema50":  0.088808,
                      "ema200":  0.08712,
                      "rsi":  47.7,
                      "atrPct":  2.31,
                      "funding8h":  9.4E-05,
                      "barTime":  1784476800000,
                      "distZonePct":  -0.21,
                      "sub":  {
                                  "trendOk":  false,
                                  "pullback":  false,
                                  "rsiReset":  false,
                                  "triggerBar":  false
                              },
                      "checks":  {
                                     "setupA":  false,
                                     "btcFilter":  true,
                                     "flatMode":  true,
                                     "atrCap":  true,
                                     "funding":  true,
                                     "fearGreed":  true
                                 },
                      "pass":  false,
                      "entry":  null,
                      "stop":  null,
                      "tp1":  null,
                      "stopPct":  null,
                      "rr":  null,
                      "qty":  null,
                      "riskUsd":  100.17
                  },
                  {
                      "symbol":  "SUI-USDT",
                      "side":  null,
                      "trend":  "up",
                      "dir":  "long",
                      "price":  0.7488,
                      "ema20":  0.74329,
                      "ema50":  0.740874,
                      "ema200":  0.757042,
                      "rsi":  55.9,
                      "atrPct":  1.42,
                      "funding8h":  0.0001,
                      "barTime":  1784476800000,
                      "distZonePct":  0.74,
                      "sub":  {
                                  "trendOk":  true,
                                  "pullback":  true,
                                  "rsiReset":  false,
                                  "triggerBar":  false
                              },
                      "checks":  {
                                     "setupA":  false,
                                     "btcFilter":  true,
                                     "flatMode":  true,
                                     "atrCap":  true,
                                     "funding":  true,
                                     "fearGreed":  true
                                 },
                      "pass":  false,
                      "entry":  null,
                      "stop":  null,
                      "tp1":  null,
                      "stopPct":  null,
                      "rr":  null,
                      "qty":  null,
                      "riskUsd":  100.17
                  },
                  {
                      "symbol":  "AAVE-USDT",
                      "side":  null,
                      "trend":  "down",
                      "dir":  "down",
                      "price":  89.06,
                      "ema20":  90.624512,
                      "ema50":  92.229695,
                      "ema200":  88.572824,
                      "rsi":  38.6,
                      "atrPct":  1.62,
                      "funding8h":  -5.1E-05,
                      "barTime":  1784476800000,
                      "distZonePct":  -1.76,
                      "sub":  {
                                  "trendOk":  true,
                                  "pullback":  true,
                                  "rsiReset":  false,
                                  "triggerBar":  false
                              },
                      "checks":  {
                                     "setupA":  false,
                                     "btcFilter":  true,
                                     "flatMode":  true,
                                     "atrCap":  true,
                                     "funding":  true,
                                     "fearGreed":  true
                                 },
                      "pass":  false,
                      "entry":  null,
                      "stop":  null,
                      "tp1":  null,
                      "stopPct":  null,
                      "rr":  null,
                      "qty":  null,
                      "riskUsd":  100.17
                  }
              ]
}
