{
    "scannedUtc":  "2026-07-18 16:08",
    "strategy":  "v2",
    "btcTrend":  "up",
    "flatBlockAll":  false,
    "fng":  25,
    "closedBarUtc":  "2026-07-18 12:00",
    "signals":  [

                ],
    "watch":  [
                  {
                      "symbol":  "BTC-USDT",
                      "side":  null,
                      "trend":  "up",
                      "dir":  "long",
                      "price":  64090.9,
                      "ema20":  63946.947909,
                      "ema50":  63747.051882,
                      "ema200":  64116.682945,
                      "rsi":  52.2,
                      "atrPct":  0.9,
                      "funding8h":  8.6E-05,
                      "barTime":  1784376000000,
                      "distZonePct":  0.22,
                      "sub":  {
                                  "trendOk":  true,
                                  "pullback":  true,
                                  "rsiReset":  false,
                                  "triggerBar":  false
                              },
                      "checks":  {
                                     "setupA":  false,
                                     "btcFilter":  true,
                                     "flatMode":  true,
                                     "atrCap":  true,
                                     "funding":  true,
                                     "fearGreed":  true
                                 },
                      "pass":  false,
                      "entry":  null,
                      "stop":  null,
                      "tp1":  null,
                      "stopPct":  null,
                      "rr":  null,
                      "qty":  null,
                      "riskUsd":  98.98
                  },
                  {
                      "symbol":  "ETH-USDT",
                      "side":  null,
                      "trend":  "up",
                      "dir":  "long",
                      "price":  1843.1,
                      "ema20":  1851.071318,
                      "ema50":  1831.044532,
                      "ema200":  1787.656997,
                      "rsi":  47.8,
                      "atrPct":  1.23,
                      "funding8h":  3E-05,
                      "barTime":  1784376000000,
                      "distZonePct":  0,
                      "sub":  {
                                  "trendOk":  true,
                                  "pullback":  true,
                                  "rsiReset":  true,
                                  "triggerBar":  false
                              },
                      "checks":  {
                                     "setupA":  false,
                                     "btcFilter":  true,
                                     "flatMode":  true,
                                     "atrCap":  true,
                                     "funding":  true,
                                     "fearGreed":  true
                                 },
                      "pass":  false,
                      "entry":  null,
                      "stop":  null,
                      "tp1":  null,
                      "stopPct":  null,
                      "rr":  null,
                      "qty":  null,
                      "riskUsd":  98.98
                  },
                  {
                      "symbol":  "SOL-USDT",
                      "side":  null,
                      "trend":  "down",
                      "dir":  "down",
                      "price":  74.929,
                      "ema20":  75.567635,
                      "ema50":  76.413274,
                      "ema200":  76.558466,
                      "rsi":  40,
                      "atrPct":  1.23,
                      "funding8h":  0.0001,
                      "barTime":  1784376000000,
                      "distZonePct":  -0.85,
                      "sub":  {
                                  "trendOk":  true,
                                  "pullback":  false,
                                  "rsiReset":  false,
                                  "triggerBar":  false
                              },
                      "checks":  {
                                     "setupA":  false,
                                     "btcFilter":  true,
                                     "flatMode":  true,
                                     "atrCap":  true,
                                     "funding":  true,
                                     "fearGreed":  true
                                 },
                      "pass":  false,
                      "entry":  null,
                      "stop":  null,
                      "tp1":  null,
                      "stopPct":  null,
                      "rr":  null,
                      "qty":  null,
                      "riskUsd":  98.98
                  },
                  {
                      "symbol":  "BNB-USDT",
                      "side":  null,
                      "trend":  "down",
                      "dir":  "down",
                      "price":  570.37,
                      "ema20":  571.305659,
                      "ema50":  572.919539,
                      "ema200":  581.77233,
                      "rsi":  46.8,
                      "atrPct":  0.82,
                      "funding8h":  0.0001,
                      "barTime":  1784376000000,
                      "distZonePct":  -0.16,
                      "sub":  {
                                  "trendOk":  true,
                                  "pullback":  false,
                                  "rsiReset":  false,
                                  "triggerBar":  false
                              },
                      "checks":  {
                                     "setupA":  false,
                                     "btcFilter":  true,
                                     "flatMode":  true,
                                     "atrCap":  true,
                                     "funding":  true,
                                     "fearGreed":  true
                                 },
                      "pass":  false,
                      "entry":  null,
                      "stop":  null,
                      "tp1":  null,
                      "stopPct":  null,
                      "rr":  null,
                      "qty":  null,
                      "riskUsd":  98.98
                  },
                  {
                      "symbol":  "XRP-USDT",
                      "side":  null,
                      "trend":  "down",
                      "dir":  "down",
                      "price":  1.0855,
                      "ema20":  1.09228,
                      "ema50":  1.095651,
                      "ema200":  1.125154,
                      "rsi":  44.1,
                      "atrPct":  1.1,
                      "funding8h":  5E-05,
                      "barTime":  1784376000000,
                      "distZonePct":  -0.62,
                      "sub":  {
                                  "trendOk":  true,
                                  "pullback":  false,
                                  "rsiReset":  false,
                                  "triggerBar":  false
                              },
                      "checks":  {
                                     "setupA":  false,
                                     "btcFilter":  true,
                                     "flatMode":  true,
                                     "atrCap":  true,
                                     "funding":  true,
                                     "fearGreed":  true
                                 },
                      "pass":  false,
                      "entry":  null,
                      "stop":  null,
                      "tp1":  null,
                      "stopPct":  null,
                      "rr":  null,
                      "qty":  null,
                      "riskUsd":  98.98
                  },
                  {
                      "symbol":  "DOGE-USDT",
                      "side":  null,
                      "trend":  "down",
                      "dir":  "down",
                      "price":  0.07215,
                      "ema20":  0.072689,
                      "ema50":  0.073177,
                      "ema200":  0.077977,
                      "rsi":  42.2,
                      "atrPct":  1.24,
                      "funding8h":  0.0001,
                      "barTime":  1784376000000,
                      "distZonePct":  -0.75,
                      "sub":  {
                                  "trendOk":  true,
                                  "pullback":  false,
                                  "rsiReset":  false,
                                  "triggerBar":  false
                              },
                      "checks":  {
                                     "setupA":  false,
                                     "btcFilter":  true,
                                     "flatMode":  true,
                                     "atrCap":  true,
                                     "funding":  true,
                                     "fearGreed":  true
                                 },
                      "pass":  false,
                      "entry":  null,
                      "stop":  null,
                      "tp1":  null,
                      "stopPct":  null,
                      "rr":  null,
                      "qty":  null,
                      "riskUsd":  98.98
                  },
                  {
                      "symbol":  "ADA-USDT",
                      "side":  null,
                      "trend":  "down",
                      "dir":  "down",
                      "price":  0.1645,
                      "ema20":  0.164023,
                      "ema50":  0.164505,
                      "ema200":  0.171371,
                      "rsi":  51.5,
                      "atrPct":  1.98,
                      "funding8h":  0.0001,
                      "barTime":  1784376000000,
                      "distZonePct":  0,
                      "sub":  {
                                  "trendOk":  true,
                                  "pullback":  true,
                                  "rsiReset":  true,
                                  "triggerBar":  false
                              },
                      "checks":  {
                                     "setupA":  false,
                                     "btcFilter":  true,
                                     "flatMode":  true,
                                     "atrCap":  true,
                                     "funding":  true,
                                     "fearGreed":  true
                                 },
                      "pass":  false,
                      "entry":  null,
                      "stop":  null,
                      "tp1":  null,
                      "stopPct":  null,
                      "rr":  null,
                      "qty":  null,
                      "riskUsd":  98.98
                  },
                  {
                      "symbol":  "AVAX-USDT",
                      "side":  null,
                      "trend":  "down",
                      "dir":  "down",
                      "price":  6.538,
                      "ema20":  6.571837,
                      "ema50":  6.594461,
                      "ema200":  6.833882,
                      "rsi":  46.5,
                      "atrPct":  1.61,
                      "funding8h":  6.76E-05,
                      "barTime":  1784376000000,
                      "distZonePct":  -0.52,
                      "sub":  {
                                  "trendOk":  true,
                                  "pullback":  true,
                                  "rsiReset":  true,
                                  "triggerBar":  false
                              },
                      "checks":  {
                                     "setupA":  false,
                                     "btcFilter":  true,
                                     "flatMode":  true,
                                     "atrCap":  true,
                                     "funding":  true,
                                     "fearGreed":  true
                                 },
                      "pass":  false,
                      "entry":  null,
                      "stop":  null,
                      "tp1":  null,
                      "stopPct":  null,
                      "rr":  null,
                      "qty":  null,
                      "riskUsd":  98.98
                  },
                  {
                      "symbol":  "LINK-USDT",
                      "side":  null,
                      "trend":  "up",
                      "dir":  "long",
                      "price":  8.271,
                      "ema20":  8.271843,
                      "ema50":  8.167022,
                      "ema200":  8.057573,
                      "rsi":  51.6,
                      "atrPct":  1.37,
                      "funding8h":  6.94E-05,
                      "barTime":  1784376000000,
                      "distZonePct":  0,
                      "sub":  {
                                  "trendOk":  true,
                                  "pullback":  true,
                                  "rsiReset":  true,
                                  "triggerBar":  false
                              },
                      "checks":  {
                                     "setupA":  false,
                                     "btcFilter":  true,
                                     "flatMode":  true,
                                     "atrCap":  true,
                                     "funding":  true,
                                     "fearGreed":  true
                                 },
                      "pass":  false,
                      "entry":  null,
                      "stop":  null,
                      "tp1":  null,
                      "stopPct":  null,
                      "rr":  null,
                      "qty":  null,
                      "riskUsd":  98.98
                  },
                  {
                      "symbol":  "DOT-USDT",
                      "side":  null,
                      "trend":  "down",
                      "dir":  "down",
                      "price":  0.831,
                      "ema20":  0.845925,
                      "ema50":  0.848298,
                      "ema200":  0.900873,
                      "rsi":  39.3,
                      "atrPct":  1.83,
                      "funding8h":  0.0001,
                      "barTime":  1784376000000,
                      "distZonePct":  -1.8,
                      "sub":  {
                                  "trendOk":  true,
                                  "pullback":  true,
                                  "rsiReset":  true,
                                  "triggerBar":  false
                              },
                      "checks":  {
                                     "setupA":  false,
                                     "btcFilter":  true,
                                     "flatMode":  true,
                                     "atrCap":  true,
                                     "funding":  true,
                                     "fearGreed":  true
                                 },
                      "pass":  false,
                      "entry":  null,
                      "stop":  null,
                      "tp1":  null,
                      "stopPct":  null,
                      "rr":  null,
                      "qty":  null,
                      "riskUsd":  98.98
                  },
                  {
                      "symbol":  "LTC-USDT",
                      "side":  null,
                      "trend":  "up",
                      "dir":  "long",
                      "price":  46.22,
                      "ema20":  45.146006,
                      "ema50":  44.768364,
                      "ema200":  44.923691,
                      "rsi":  63.7,
                      "atrPct":  1.37,
                      "funding8h":  0.0001,
                      "barTime":  1784376000000,
                      "distZonePct":  2.32,
                      "sub":  {
                                  "trendOk":  true,
                                  "pullback":  false,
                                  "rsiReset":  false,
                                  "triggerBar":  false
                              },
                      "checks":  {
                                     "setupA":  false,
                                     "btcFilter":  true,
                                     "flatMode":  true,
                                     "atrCap":  true,
                                     "funding":  true,
                                     "fearGreed":  true
                                 },
                      "pass":  false,
                      "entry":  null,
                      "stop":  null,
                      "tp1":  null,
                      "stopPct":  null,
                      "rr":  null,
                      "qty":  null,
                      "riskUsd":  98.98
                  },
                  {
                      "symbol":  "BCH-USDT",
                      "side":  null,
                      "trend":  "down",
                      "dir":  "down",
                      "price":  219.59,
                      "ema20":  223.046387,
                      "ema50":  228.674012,
                      "ema200":  235.360506,
                      "rsi":  36.6,
                      "atrPct":  1.77,
                      "funding8h":  9.7E-05,
                      "barTime":  1784376000000,
                      "distZonePct":  -1.57,
                      "sub":  {
                                  "trendOk":  true,
                                  "pullback":  false,
                                  "rsiReset":  false,
                                  "triggerBar":  false
                              },
                      "checks":  {
                                     "setupA":  false,
                                     "btcFilter":  true,
                                     "flatMode":  true,
                                     "atrCap":  true,
                                     "funding":  true,
                                     "fearGreed":  true
                                 },
                      "pass":  false,
                      "entry":  null,
                      "stop":  null,
                      "tp1":  null,
                      "stopPct":  null,
                      "rr":  null,
                      "qty":  null,
                      "riskUsd":  98.98
                  },
                  {
                      "symbol":  "UNI-USDT",
                      "side":  null,
                      "trend":  "range",
                      "dir":  null,
                      "price":  3.514,
                      "ema20":  3.564085,
                      "ema50":  3.534872,
                      "ema200":  3.282892,
                      "rsi":  45,
                      "atrPct":  2.44,
                      "funding8h":  -0.000183,
                      "barTime":  1784376000000,
                      "distZonePct":  -0.59,
                      "sub":  {
                                  "trendOk":  false,
                                  "pullback":  false,
                                  "rsiReset":  false,
                                  "triggerBar":  false
                              },
                      "checks":  {
                                     "setupA":  false,
                                     "btcFilter":  true,
                                     "flatMode":  true,
                                     "atrCap":  true,
                                     "funding":  true,
                                     "fearGreed":  true
                                 },
                      "pass":  false,
                      "entry":  null,
                      "stop":  null,
                      "tp1":  null,
                      "stopPct":  null,
                      "rr":  null,
                      "qty":  null,
                      "riskUsd":  98.98
                  },
                  {
                      "symbol":  "ATOM-USDT",
                      "side":  null,
                      "trend":  "down",
                      "dir":  "down",
                      "price":  1.491,
                      "ema20":  1.516479,
                      "ema50":  1.538453,
                      "ema200":  1.639374,
                      "rsi":  33,
                      "atrPct":  1.33,
                      "funding8h":  0.0001,
                      "barTime":  1784376000000,
                      "distZonePct":  -1.71,
                      "sub":  {
                                  "trendOk":  true,
                                  "pullback":  false,
                                  "rsiReset":  false,
                                  "triggerBar":  false
                              },
                      "checks":  {
                                     "setupA":  false,
                                     "btcFilter":  true,
                                     "flatMode":  true,
                                     "atrCap":  true,
                                     "funding":  true,
                                     "fearGreed":  true
                                 },
                      "pass":  false,
                      "entry":  null,
                      "stop":  null,
                      "tp1":  null,
                      "stopPct":  null,
                      "rr":  null,
                      "qty":  null,
                      "riskUsd":  98.98
                  },
                  {
                      "symbol":  "NEAR-USDT",
                      "side":  null,
                      "trend":  "down",
                      "dir":  "down",
                      "price":  1.916,
                      "ema20":  1.955642,
                      "ema50":  1.959651,
                      "ema200":  1.9822,
                      "rsi":  41.7,
                      "atrPct":  2.35,
                      "funding8h":  0.0001,
                      "barTime":  1784376000000,
                      "distZonePct":  -2.07,
                      "sub":  {
                                  "trendOk":  true,
                                  "pullback":  false,
                                  "rsiReset":  false,
                                  "triggerBar":  false
                              },
                      "checks":  {
                                     "setupA":  false,
                                     "btcFilter":  true,
                                     "flatMode":  true,
                                     "atrCap":  true,
                                     "funding":  true,
                                     "fearGreed":  true
                                 },
                      "pass":  false,
                      "entry":  null,
                      "stop":  null,
                      "tp1":  null,
                      "stopPct":  null,
                      "rr":  null,
                      "qty":  null,
                      "riskUsd":  98.98
                  },
                  {
                      "symbol":  "OP-USDT",
                      "side":  null,
                      "trend":  "down",
                      "dir":  "down",
                      "price":  0.0946,
                      "ema20":  0.09775,
                      "ema50":  0.099752,
                      "ema200":  0.104104,
                      "rsi":  32.5,
                      "atrPct":  2.11,
                      "funding8h":  0.0001,
                      "barTime":  1784376000000,
                      "distZonePct":  -3.33,
                      "sub":  {
                                  "trendOk":  true,
                                  "pullback":  false,
                                  "rsiReset":  false,
                                  "triggerBar":  false
                              },
                      "checks":  {
                                     "setupA":  false,
                                     "btcFilter":  true,
                                     "flatMode":  true,
                                     "atrCap":  true,
                                     "funding":  true,
                                     "fearGreed":  true
                                 },
                      "pass":  false,
                      "entry":  null,
                      "stop":  null,
                      "tp1":  null,
                      "stopPct":  null,
                      "rr":  null,
                      "qty":  null,
                      "riskUsd":  98.98
                  },
                  {
                      "symbol":  "APT-USDT",
                      "side":  null,
                      "trend":  "down",
                      "dir":  "down",
                      "price":  0.6049,
                      "ema20":  0.612312,
                      "ema50":  0.614642,
                      "ema200":  0.650525,
                      "rsi":  44.6,
                      "atrPct":  1.9,
                      "funding8h":  0.0001,
                      "barTime":  1784376000000,
                      "distZonePct":  -1.23,
                      "sub":  {
                                  "trendOk":  true,
                                  "pullback":  true,
                                  "rsiReset":  true,
                                  "triggerBar":  false
                              },
                      "checks":  {
                                     "setupA":  false,
                                     "btcFilter":  true,
                                     "flatMode":  true,
                                     "atrCap":  true,
                                     "funding":  true,
                                     "fearGreed":  true
                                 },
                      "pass":  false,
                      "entry":  null,
                      "stop":  null,
                      "tp1":  null,
                      "stopPct":  null,
                      "rr":  null,
                      "qty":  null,
                      "riskUsd":  98.98
                  },
                  {
                      "symbol":  "ARB-USDT",
                      "side":  null,
                      "trend":  "range",
                      "dir":  null,
                      "price":  0.08846,
                      "ema20":  0.089451,
                      "ema50":  0.088894,
                      "ema200":  0.087096,
                      "rsi":  46,
                      "atrPct":  2.75,
                      "funding8h":  5.6E-05,
                      "barTime":  1784376000000,
                      "distZonePct":  -0.49,
                      "sub":  {
                                  "trendOk":  false,
                                  "pullback":  false,
                                  "rsiReset":  false,
                                  "triggerBar":  false
                              },
                      "checks":  {
                                     "setupA":  false,
                                     "btcFilter":  true,
                                     "flatMode":  true,
                                     "atrCap":  true,
                                     "funding":  true,
                                     "fearGreed":  true
                                 },
                      "pass":  false,
                      "entry":  null,
                      "stop":  null,
                      "tp1":  null,
                      "stopPct":  null,
                      "rr":  null,
                      "qty":  null,
                      "riskUsd":  98.98
                  },
                  {
                      "symbol":  "SUI-USDT",
                      "side":  null,
                      "trend":  "range",
                      "dir":  null,
                      "price":  0.7348,
                      "ema20":  0.740186,
                      "ema50":  0.739227,
                      "ema200":  0.75857,
                      "rsi":  45.4,
                      "atrPct":  1.58,
                      "funding8h":  1.1E-05,
                      "barTime":  1784376000000,
                      "distZonePct":  -0.6,
                      "sub":  {
                                  "trendOk":  false,
                                  "pullback":  false,
                                  "rsiReset":  false,
                                  "triggerBar":  false
                              },
                      "checks":  {
                                     "setupA":  false,
                                     "btcFilter":  true,
                                     "flatMode":  true,
                                     "atrCap":  true,
                                     "funding":  true,
                                     "fearGreed":  true
                                 },
                      "pass":  false,
                      "entry":  null,
                      "stop":  null,
                      "tp1":  null,
                      "stopPct":  null,
                      "rr":  null,
                      "qty":  null,
                      "riskUsd":  98.98
                  },
                  {
                      "symbol":  "AAVE-USDT",
                      "side":  null,
                      "trend":  "down",
                      "dir":  "down",
                      "price":  88.79,
                      "ema20":  91.583788,
                      "ema50":  93.045353,
                      "ema200":  88.519267,
                      "rsi":  33.5,
                      "atrPct":  1.92,
                      "funding8h":  0.0001,
                      "barTime":  1784376000000,
                      "distZonePct":  -3.15,
                      "sub":  {
                                  "trendOk":  true,
                                  "pullback":  false,
                                  "rsiReset":  false,
                                  "triggerBar":  false
                              },
                      "checks":  {
                                     "setupA":  false,
                                     "btcFilter":  true,
                                     "flatMode":  true,
                                     "atrCap":  true,
                                     "funding":  true,
                                     "fearGreed":  true
                                 },
                      "pass":  false,
                      "entry":  null,
                      "stop":  null,
                      "tp1":  null,
                      "stopPct":  null,
                      "rr":  null,
                      "qty":  null,
                      "riskUsd":  98.98
                  }
              ]
}
