{
  "scannedUtc": "2026-07-14 08:00",
  "strategy": "v2",
  "btcTrend": "range",
  "flatBlockAll": true,
  "fng": 22,
  "closedBarUtc": "2026-07-14 04:00",
  "signals": [],
  "watch": [
    {
      "symbol": "BTC-USDT",
      "side": null,
      "trend": "range",
      "dir": null,
      "price": 62521.9,
      "ema20": 63140.061096,
      "ema50": 63079.03177,
      "ema200": 64049.3036,
      "rsi": 39.7,
      "atrPct": 0.99,
      "funding8h": 0.0001,
      "barTime": 1784001600000,
      "distZonePct": -0.89,
      "sub": {
        "trendOk": false,
        "pullback": false,
        "rsiReset": false,
        "triggerBar": false
      },
      "checks": {
        "setupA": false,
        "btcFilter": true,
        "flatMode": false,
        "atrCap": true,
        "funding": true,
        "fearGreed": true
      },
      "pass": false,
      "entry": null,
      "stop": null,
      "tp1": null,
      "stopPct": null,
      "rr": null,
      "qty": null,
      "riskUsd": 1.18
    },
    {
      "symbol": "ETH-USDT",
      "side": null,
      "trend": "up",
      "dir": "long",
      "price": 1780.0,
      "ema20": 1786.703786,
      "ema50": 1771.416629,
      "ema200": 1763.07682,
      "rsi": 48.0,
      "atrPct": 1.37,
      "funding8h": 0.0001,
      "barTime": 1784001600000,
      "distZonePct": 0,
      "sub": {
        "trendOk": true,
        "pullback": true,
        "rsiReset": true,
        "triggerBar": false
      },
      "checks": {
        "setupA": false,
        "btcFilter": true,
        "flatMode": false,
        "atrCap": true,
        "funding": true,
        "fearGreed": true
      },
      "pass": false,
      "entry": null,
      "stop": null,
      "tp1": null,
      "stopPct": null,
      "rr": null,
      "qty": null,
      "riskUsd": 1.18
    },
    {
      "symbol": "SOL-USDT",
      "side": null,
      "trend": "down",
      "dir": "down",
      "price": 74.91,
      "ema20": 76.465648,
      "ema50": 77.439839,
      "ema200": 76.635081,
      "rsi": 33.7,
      "atrPct": 1.56,
      "funding8h": 0.0001,
      "barTime": 1784001600000,
      "distZonePct": -2.08,
      "sub": {
        "trendOk": true,
        "pullback": false,
        "rsiReset": false,
        "triggerBar": false
      },
      "checks": {
        "setupA": false,
        "btcFilter": true,
        "flatMode": false,
        "atrCap": true,
        "funding": true,
        "fearGreed": true
      },
      "pass": false,
      "entry": null,
      "stop": null,
      "tp1": null,
      "stopPct": null,
      "rr": null,
      "qty": null,
      "riskUsd": 1.18
    },
    {
      "symbol": "BNB-USDT",
      "side": null,
      "trend": "down",
      "dir": "down",
      "price": 569.9,
      "ema20": 571.874601,
      "ema50": 572.413765,
      "ema200": 583.096955,
      "rsi": 45.8,
      "atrPct": 0.96,
      "funding8h": 0.0001,
      "barTime": 1784001600000,
      "distZonePct": -0.35,
      "sub": {
        "trendOk": true,
        "pullback": false,
        "rsiReset": false,
        "triggerBar": false
      },
      "checks": {
        "setupA": false,
        "btcFilter": true,
        "flatMode": false,
        "atrCap": true,
        "funding": true,
        "fearGreed": true
      },
      "pass": false,
      "entry": null,
      "stop": null,
      "tp1": null,
      "stopPct": null,
      "rr": null,
      "qty": null,
      "riskUsd": 1.18
    },
    {
      "symbol": "XRP-USDT",
      "side": null,
      "trend": "down",
      "dir": "down",
      "price": 1.0683,
      "ema20": 1.083878,
      "ema50": 1.094648,
      "ema200": 1.131935,
      "rsi": 35.9,
      "atrPct": 1.26,
      "funding8h": 0.0001,
      "barTime": 1784001600000,
      "distZonePct": -1.46,
      "sub": {
        "trendOk": true,
        "pullback": false,
        "rsiReset": false,
        "triggerBar": false
      },
      "checks": {
        "setupA": false,
        "btcFilter": true,
        "flatMode": false,
        "atrCap": true,
        "funding": true,
        "fearGreed": true
      },
      "pass": false,
      "entry": null,
      "stop": null,
      "tp1": null,
      "stopPct": null,
      "rr": null,
      "qty": null,
      "riskUsd": 1.18
    },
    {
      "symbol": "DOGE-USDT",
      "side": null,
      "trend": "down",
      "dir": "down",
      "price": 0.07213,
      "ema20": 0.072789,
      "ema50": 0.073588,
      "ema200": 0.079327,
      "rsi": 40.3,
      "atrPct": 1.38,
      "funding8h": 0.0001,
      "barTime": 1784001600000,
      "distZonePct": -0.91,
      "sub": {
        "trendOk": true,
        "pullback": false,
        "rsiReset": false,
        "triggerBar": false
      },
      "checks": {
        "setupA": false,
        "btcFilter": true,
        "flatMode": false,
        "atrCap": true,
        "funding": true,
        "fearGreed": true
      },
      "pass": false,
      "entry": null,
      "stop": null,
      "tp1": null,
      "stopPct": null,
      "rr": null,
      "qty": null,
      "riskUsd": 1.18
    },
    {
      "symbol": "ADA-USDT",
      "side": null,
      "trend": "down",
      "dir": "down",
      "price": 0.1586,
      "ema20": 0.162149,
      "ema50": 0.1657,
      "ema200": 0.173301,
      "rsi": 35.3,
      "atrPct": 1.99,
      "funding8h": 0.0001,
      "barTime": 1784001600000,
      "distZonePct": -2.24,
      "sub": {
        "trendOk": true,
        "pullback": false,
        "rsiReset": false,
        "triggerBar": false
      },
      "checks": {
        "setupA": false,
        "btcFilter": true,
        "flatMode": false,
        "atrCap": true,
        "funding": true,
        "fearGreed": true
      },
      "pass": false,
      "entry": null,
      "stop": null,
      "tp1": null,
      "stopPct": null,
      "rr": null,
      "qty": null,
      "riskUsd": 1.18
    },
    {
      "symbol": "AVAX-USDT",
      "side": null,
      "trend": "down",
      "dir": "down",
      "price": 6.477,
      "ema20": 6.53305,
      "ema50": 6.605288,
      "ema200": 6.886763,
      "rsi": 44.2,
      "atrPct": 1.83,
      "funding8h": 0.0001,
      "barTime": 1784001600000,
      "distZonePct": -0.87,
      "sub": {
        "trendOk": true,
        "pullback": true,
        "rsiReset": false,
        "triggerBar": false
      },
      "checks": {
        "setupA": false,
        "btcFilter": true,
        "flatMode": false,
        "atrCap": true,
        "funding": true,
        "fearGreed": true
      },
      "pass": false,
      "entry": null,
      "stop": null,
      "tp1": null,
      "stopPct": null,
      "rr": null,
      "qty": null,
      "riskUsd": 1.18
    },
    {
      "symbol": "LINK-USDT",
      "side": null,
      "trend": "up",
      "dir": "long",
      "price": 7.919,
      "ema20": 7.938916,
      "ema50": 7.888322,
      "ema200": 7.973993,
      "rsi": 49.0,
      "atrPct": 1.49,
      "funding8h": 0.0001,
      "barTime": 1784001600000,
      "distZonePct": 0,
      "sub": {
        "trendOk": true,
        "pullback": true,
        "rsiReset": true,
        "triggerBar": false
      },
      "checks": {
        "setupA": false,
        "btcFilter": true,
        "flatMode": false,
        "atrCap": true,
        "funding": true,
        "fearGreed": true
      },
      "pass": false,
      "entry": null,
      "stop": null,
      "tp1": null,
      "stopPct": null,
      "rr": null,
      "qty": null,
      "riskUsd": 1.18
    },
    {
      "symbol": "DOT-USDT",
      "side": null,
      "trend": "down",
      "dir": "down",
      "price": 0.8444,
      "ema20": 0.845214,
      "ema50": 0.850926,
      "ema200": 0.915836,
      "rsi": 48.3,
      "atrPct": 1.85,
      "funding8h": 0.0001,
      "barTime": 1784001600000,
      "distZonePct": -0.1,
      "sub": {
        "trendOk": true,
        "pullback": false,
        "rsiReset": false,
        "triggerBar": false
      },
      "checks": {
        "setupA": false,
        "btcFilter": true,
        "flatMode": false,
        "atrCap": true,
        "funding": true,
        "fearGreed": true
      },
      "pass": false,
      "entry": null,
      "stop": null,
      "tp1": null,
      "stopPct": null,
      "rr": null,
      "qty": null,
      "riskUsd": 1.18
    },
    {
      "symbol": "LTC-USDT",
      "side": null,
      "trend": "down",
      "dir": "down",
      "price": 43.56,
      "ema20": 43.985281,
      "ema50": 44.084151,
      "ema200": 44.833038,
      "rsi": 42.2,
      "atrPct": 1.24,
      "funding8h": 0.0001,
      "barTime": 1784001600000,
      "distZonePct": -0.98,
      "sub": {
        "trendOk": true,
        "pullback": false,
        "rsiReset": false,
        "triggerBar": false
      },
      "checks": {
        "setupA": false,
        "btcFilter": true,
        "flatMode": false,
        "atrCap": true,
        "funding": true,
        "fearGreed": true
      },
      "pass": false,
      "entry": null,
      "stop": null,
      "tp1": null,
      "stopPct": null,
      "rr": null,
      "qty": null,
      "riskUsd": 1.18
    },
    {
      "symbol": "BCH-USDT",
      "side": null,
      "trend": "range",
      "dir": null,
      "price": 234.8,
      "ema20": 239.396861,
      "ema50": 237.576016,
      "ema200": 238.230457,
      "rsi": 40.0,
      "atrPct": 1.93,
      "funding8h": 0.0001,
      "barTime": 1784001600000,
      "distZonePct": -1.18,
      "sub": {
        "trendOk": false,
        "pullback": false,
        "rsiReset": false,
        "triggerBar": false
      },
      "checks": {
        "setupA": false,
        "btcFilter": true,
        "flatMode": false,
        "atrCap": true,
        "funding": true,
        "fearGreed": true
      },
      "pass": false,
      "entry": null,
      "stop": null,
      "tp1": null,
      "stopPct": null,
      "rr": null,
      "qty": null,
      "riskUsd": 1.18
    },
    {
      "symbol": "UNI-USDT",
      "side": null,
      "trend": "up",
      "dir": "long",
      "price": 3.572,
      "ema20": 3.552622,
      "ema50": 3.441313,
      "ema200": 3.186017,
      "rsi": 54.1,
      "atrPct": 2.88,
      "funding8h": 0.0001,
      "barTime": 1784001600000,
      "distZonePct": 0.54,
      "sub": {
        "trendOk": true,
        "pullback": true,
        "rsiReset": true,
        "triggerBar": false
      },
      "checks": {
        "setupA": false,
        "btcFilter": true,
        "flatMode": false,
        "atrCap": true,
        "funding": true,
        "fearGreed": true
      },
      "pass": false,
      "entry": null,
      "stop": null,
      "tp1": null,
      "stopPct": null,
      "rr": null,
      "qty": null,
      "riskUsd": 1.18
    },
    {
      "symbol": "ATOM-USDT",
      "side": null,
      "trend": "down",
      "dir": "down",
      "price": 1.5257,
      "ema20": 1.55441,
      "ema50": 1.566528,
      "ema200": 1.670781,
      "rsi": 37.8,
      "atrPct": 1.59,
      "funding8h": 0.0001,
      "barTime": 1784001600000,
      "distZonePct": -1.88,
      "sub": {
        "trendOk": true,
        "pullback": false,
        "rsiReset": false,
        "triggerBar": false
      },
      "checks": {
        "setupA": false,
        "btcFilter": true,
        "flatMode": false,
        "atrCap": true,
        "funding": true,
        "fearGreed": true
      },
      "pass": false,
      "entry": null,
      "stop": null,
      "tp1": null,
      "stopPct": null,
      "rr": null,
      "qty": null,
      "riskUsd": 1.18
    },
    {
      "symbol": "NEAR-USDT",
      "side": null,
      "trend": "range",
      "dir": null,
      "price": 1.9914,
      "ema20": 1.920047,
      "ema50": 1.924118,
      "ema200": 1.971212,
      "rsi": 62.4,
      "atrPct": 2.58,
      "funding8h": 0.0001,
      "barTime": 1784001600000,
      "distZonePct": 3.38,
      "sub": {
        "trendOk": false,
        "pullback": false,
        "rsiReset": false,
        "triggerBar": false
      },
      "checks": {
        "setupA": false,
        "btcFilter": true,
        "flatMode": false,
        "atrCap": true,
        "funding": true,
        "fearGreed": true
      },
      "pass": false,
      "entry": null,
      "stop": null,
      "tp1": null,
      "stopPct": null,
      "rr": null,
      "qty": null,
      "riskUsd": 1.18
    },
    {
      "symbol": "OP-USDT",
      "side": null,
      "trend": "down",
      "dir": "down",
      "price": 0.10043,
      "ema20": 0.100873,
      "ema50": 0.10208,
      "ema200": 0.105765,
      "rsi": 46.1,
      "atrPct": 2.3,
      "funding8h": 0.0001,
      "barTime": 1784001600000,
      "distZonePct": -0.44,
      "sub": {
        "trendOk": true,
        "pullback": false,
        "rsiReset": false,
        "triggerBar": false
      },
      "checks": {
        "setupA": false,
        "btcFilter": true,
        "flatMode": false,
        "atrCap": true,
        "funding": true,
        "fearGreed": true
      },
      "pass": false,
      "entry": null,
      "stop": null,
      "tp1": null,
      "stopPct": null,
      "rr": null,
      "qty": null,
      "riskUsd": 1.18
    },
    {
      "symbol": "APT-USDT",
      "side": null,
      "trend": "down",
      "dir": "down",
      "price": 0.5988,
      "ema20": 0.609354,
      "ema50": 0.616434,
      "ema200": 0.66009,
      "rsi": 39.5,
      "atrPct": 2.11,
      "funding8h": 0.0001,
      "barTime": 1784001600000,
      "distZonePct": -1.76,
      "sub": {
        "trendOk": true,
        "pullback": false,
        "rsiReset": false,
        "triggerBar": false
      },
      "checks": {
        "setupA": false,
        "btcFilter": true,
        "flatMode": false,
        "atrCap": true,
        "funding": true,
        "fearGreed": true
      },
      "pass": false,
      "entry": null,
      "stop": null,
      "tp1": null,
      "stopPct": null,
      "rr": null,
      "qty": null,
      "riskUsd": 1.18
    },
    {
      "symbol": "ARB-USDT",
      "side": null,
      "trend": "up",
      "dir": "long",
      "price": 0.08927,
      "ema20": 0.091644,
      "ema50": 0.088296,
      "ema200": 0.086566,
      "rsi": 45.6,
      "atrPct": 3.62,
      "funding8h": 0.0001,
      "barTime": 1784001600000,
      "distZonePct": 0,
      "sub": {
        "trendOk": true,
        "pullback": true,
        "rsiReset": true,
        "triggerBar": false
      },
      "checks": {
        "setupA": false,
        "btcFilter": true,
        "flatMode": false,
        "atrCap": false,
        "funding": true,
        "fearGreed": true
      },
      "pass": false,
      "entry": null,
      "stop": null,
      "tp1": null,
      "stopPct": null,
      "rr": null,
      "qty": null,
      "riskUsd": 1.18
    },
    {
      "symbol": "SUI-USDT",
      "side": null,
      "trend": "down",
      "dir": "down",
      "price": 0.7306,
      "ema20": 0.730734,
      "ema50": 0.731164,
      "ema200": 0.760834,
      "rsi": 49.5,
      "atrPct": 1.73,
      "funding8h": 0.0001,
      "barTime": 1784001600000,
      "distZonePct": -0.02,
      "sub": {
        "trendOk": true,
        "pullback": false,
        "rsiReset": false,
        "triggerBar": false
      },
      "checks": {
        "setupA": false,
        "btcFilter": true,
        "flatMode": false,
        "atrCap": true,
        "funding": true,
        "fearGreed": true
      },
      "pass": false,
      "entry": null,
      "stop": null,
      "tp1": null,
      "stopPct": null,
      "rr": null,
      "qty": null,
      "riskUsd": 1.18
    },
    {
      "symbol": "AAVE-USDT",
      "side": null,
      "trend": "up",
      "dir": "long",
      "price": 95.2,
      "ema20": 95.66771,
      "ema50": 93.80405,
      "ema200": 86.968832,
      "rsi": 49.6,
      "atrPct": 2.38,
      "funding8h": 0.0001,
      "barTime": 1784001600000,
      "distZonePct": 0,
      "sub": {
        "trendOk": true,
        "pullback": true,
        "rsiReset": true,
        "triggerBar": false
      },
      "checks": {
        "setupA": false,
        "btcFilter": true,
        "flatMode": false,
        "atrCap": true,
        "funding": true,
        "fearGreed": true
      },
      "pass": false,
      "entry": null,
      "stop": null,
      "tp1": null,
      "stopPct": null,
      "rr": null,
      "qty": null,
      "riskUsd": 1.18
    }
  ]
}
